flask_oidc_verifier/__init__.py
flask_oidc_verifier/decorators.py
flask_oidc_verifier/jwt_parser.py
flask_oidc_verifier/verification.py
tests/__init__.py
tests/mocks.py
tests/test_decorators.py
flask_oidc_verifier_vishalkuo-0.0.1.dist-info/LICENSE
flask_oidc_verifier_vishalkuo-0.0.1.dist-info/METADATA
flask_oidc_verifier_vishalkuo-0.0.1.dist-info/WHEEL
flask_oidc_verifier_vishalkuo-0.0.1.dist-info/top_level.txt
flask_oidc_verifier_vishalkuo-0.0.1.dist-info/RECORD
